extergram/__init__.py
extergram/api_types.py
extergram/core.py
extergram/docs.py
extergram/errors.py
extergram/ui.py
extergram/utils.py
extergram/ext/__init__.py
extergram/ext/base.py
extergram/ext/callback_query_handler.py
extergram/ext/command_handler.py
extergram/ext/message_handler.py
extergram-0.7.0.dist-info/METADATA
extergram-0.7.0.dist-info/WHEEL
extergram-0.7.0.dist-info/top_level.txt
extergram-0.7.0.dist-info/RECORD
