Metadata-Version: 2.4
Name: extergram
Version: 0.7.0
Summary: A simple and convenient library for creating Telegram bots.
Author-email: WinFun15 <tibipocoxzsa@gmail.com>
Project-URL: Homepage, https://github.com/AAVTIBI1/extergram
Project-URL: Bug Tracker, https://github.com/AAVTIBI1/extergram/issues
Classifier: Programming Language :: Python :: 3
Classifier: License :: OSI Approved :: MIT License
Classifier: Operating System :: OS Independent
Classifier: Intended Audience :: Developers
Classifier: Topic :: Software Development :: Libraries :: Python Modules
Requires-Python: >=3.8
Requires-Dist: httpx>=0.23.0
